setup.py
django_ru_fields/__init__.py
django_ru_fields/forms.py
django_ru_fields/models.py
django_ru_fields/tests.py
django_ru_fields/utils.py
django_ru_fields.egg-info/PKG-INFO
django_ru_fields.egg-info/SOURCES.txt
django_ru_fields.egg-info/dependency_links.txt
django_ru_fields.egg-info/not-zip-safe
django_ru_fields.egg-info/top_level.txt