Metadata-Version: 1.1
Name: django-ru-fields
Version: 0.1.0
Summary: specific russian fields
Home-page: https://github.com/suvitorg/django-ru-fields
Author: Suvit Org
Author-email: mail@suvit.ru
License: UNKNOWN
Platform: UNKNOWN
Classifier: Development Status :: 5 - Production/Stable
Classifier: Framework :: Django
Classifier: License :: Free for non-commercial use
Classifier: Intended Audience :: Developers
Classifier: Intended Audience :: Manufacturing
Classifier: Intended Audience :: System Administrators
Classifier: Operating System :: OS Independent
Classifier: Programming Language :: Python
Classifier: Programming Language :: Python :: 2.7
Classifier: Environment :: Web Environment
Classifier: Topic :: Software Development
Classifier: Topic :: Office/Business
Classifier: Topic :: Office/Business :: Financial :: Point-Of-Sale
